barcelona/__init__.py
barcelona/cli.py
barcelona/scrapper.py
barcelona/screen.py
barcelona-0.1.0.dist-info/METADATA
barcelona-0.1.0.dist-info/WHEEL
barcelona-0.1.0.dist-info/entry_points.txt
barcelona-0.1.0.dist-info/RECORD
